LzFunc/__init__.py
LzFunc/core.py
lzfunc-0.1.2.dist-info/METADATA
lzfunc-0.1.2.dist-info/WHEEL
lzfunc-0.1.2.dist-info/top_level.txt
lzfunc-0.1.2.dist-info/RECORD
